EasySQL/ABC.py
EasySQL/Characters.py
EasySQL/Classes.py
EasySQL/Commands.py
EasySQL/Constraints.py
EasySQL/Decorators.py
EasySQL/EasyInstances.py
EasySQL/Exceptions.py
EasySQL/Logging.py
EasySQL/Types.py
EasySQL/Where.py
EasySQL/__init__.py
pyeasysql_ashenguard-3.2.0.dist-info/LICENSE.md
pyeasysql_ashenguard-3.2.0.dist-info/METADATA
pyeasysql_ashenguard-3.2.0.dist-info/WHEEL
pyeasysql_ashenguard-3.2.0.dist-info/top_level.txt
pyeasysql_ashenguard-3.2.0.dist-info/RECORD
